pycocotools_fix_numpy-1.0.0.dist-info/WHEEL
pycocotools_fix_numpy-1.0.0.dist-info/top_level.txt
pycocotools_fix_numpy-1.0.0.dist-info/RECORD
pycocotools_fix_numpy-1.0.0.dist-info/METADATA
pycocotools/cocoeval.py
pycocotools/__init__.py
pycocotools/_mask.cpython-37m-x86_64-linux-gnu.so
pycocotools/coco.py
pycocotools/mask.py
