Metadata-Version: 2.1
Name: pycocotools-fix-numpy
Version: 1.0.0
Summary: Fixes numpy easy_install issue: from official APIs for the MS-COCO dataset
Home-page: UNKNOWN
Author: UNKNOWN
Author-email: UNKNOWN
License: UNKNOWN
Platform: UNKNOWN
Requires-Dist: setuptools (>=18.0)
Requires-Dist: cython (>=0.27.3)
Requires-Dist: matplotlib (>=2.1.0)
